ainexus_sdk/__init__.py
ainexus_sdk/cli.py
ainexus_sdk/client.py
ainexus_sdk/config.py
ainexus_sdk/model.py
ainexus_sdk/supabase_handler.py
ainexus_sdk-0.1.42.dist-info/WHEEL
ainexus_sdk-0.1.42.dist-info/entry_points.txt
ainexus_sdk-0.1.42.dist-info/METADATA
ainexus_sdk-0.1.42.dist-info/RECORD
