Metadata-Version: 2.4
Name: ainexus-sdk
Version: 0.1.42
Summary: This is the official SDK for Nexus, a centralized repository system for AI agents.
Keywords: agent-repository,agent-discover,agenthub,agent-management
Author: Ashutosh Singh
Author-email: Ashutosh Singh <ash04singh@gmail.com>
License-Expression: MIT
Classifier: Development Status :: 4 - Beta
Classifier: Intended Audience :: Developers
Classifier: Topic :: Software Development :: Build Tools
Classifier: Programming Language :: Python :: 3.13
Requires-Dist: a2a-sdk>=0.3.3
Requires-Dist: build>=1.3.0
Requires-Dist: httpx>=0.28.1
Requires-Dist: pydantic>=2.11.7
Requires-Dist: python-dotenv>=1.1.1
Requires-Dist: rich>=14.1.0
Requires-Dist: supabase>=2.18.1
Requires-Dist: twine>=6.1.0
Requires-Dist: typer>=0.17.3
Maintainer: Ashutosh Singh
Maintainer-email: Ashutosh Singh <ash04singh@gmail.com>
Requires-Python: >=3.10
Project-URL: Documentation, https://docs.ainexus.me/
Project-URL: Homepage, https://www.ainexus.me/
